foramgeochem/__init__.py
foramgeochem/general.py
foramgeochem/helpers.py
foramgeochem/mgca/__init__.py
foramgeochem/mgca/converters.py
foramgeochem/mgca/tfr.py
foramgeochem/resources/params.json
foramgeochem-0.0.1.dist-info/METADATA
foramgeochem-0.0.1.dist-info/RECORD
foramgeochem-0.0.1.dist-info/WHEEL
foramgeochem-0.0.1.dist-info/top_level.txt
foramgeochem-0.0.1.dist-info/zip-safe
