Metadata-Version: 2.1
Name: foramgeochem
Version: 0.0.1
Summary: Tools for converting between foraminifera geochemistry and environmental parameters.
Home-page: https://github.com/oscarbranson/foramgeochem
Author: Oscar Branson
Author-email: oscarbranson@gmail.com
License: MIT
Platform: UNKNOWN
Classifier: Development Status :: 4 - Beta
Classifier: Intended Audience :: Science/Research
Classifier: Topic :: Scientific/Engineering
Classifier: Programming Language :: Python :: 2
Classifier: Programming Language :: Python :: 3
Requires-Dist: numpy
Requires-Dist: uncertainties
